iqcli/config.py
iqcli/api/__init__.py
iqcli/api/file.py
iqcli/api/search.py
iqcli/api/session.py
iqcli/cli/__init__.py
iqcli/cli/file.py
iqcli/cli/saved_search.py
iqcli/cli/session.py
iqcli/lib/client.py
iqcli-1.0.0.dist-info/LICENSE
iqcli-1.0.0.dist-info/METADATA
iqcli-1.0.0.dist-info/WHEEL
iqcli-1.0.0.dist-info/entry_points.txt
iqcli-1.0.0.dist-info/top_level.txt
iqcli-1.0.0.dist-info/RECORD
