Metadata-Version: 2.1
Name: iqcli
Version: 1.0.0
Summary: InQuest platform v3 Python client with CLI interface.
Home-page: https://github.com/InQuest/iq-cli
Author: InQuest Labs
Author-email: labs@inquest.net
License: GPL
Classifier: Intended Audience :: Developers
Classifier: Intended Audience :: Information Technology
Classifier: Intended Audience :: System Administrators
Classifier: License :: OSI Approved :: GNU General Public License v2 (GPLv2)
Classifier: Operating System :: OS Independent
Classifier: Programming Language :: Python
Classifier: Topic :: Security
Classifier: Topic :: Software Development :: Libraries
Classifier: Topic :: Internet
License-File: LICENSE
